LICENSE
gatorconfig/__init__.py
gatorconfig/actions_configuration.py
gatorconfig/gator_config.py
gatorconfig/gui/check_file.py
gatorconfig/gui/cwidgets.py
gatorconfig/gui/form.py
gatorconfig/gui/homepage.py
gatorconfig/gui_main.py
gatorconfig/scrape_releases.py
gatorconfig-1.0.0.dist-info/entry_points.txt
gatorconfig-1.0.0.dist-info/LICENSE
gatorconfig-1.0.0.dist-info/WHEEL
gatorconfig-1.0.0.dist-info/METADATA
gatorconfig-1.0.0.dist-info/RECORD
