Metadata-Version: 2.1
Name: gatorconfig
Version: 1.0.0
Summary: Autogeneration of GatorGradle configuration files.
Home-page: https://github.com/cmpsc-481-s22-m1/GatorConfig
License: MIT
Author: Daniel Ullrich
Requires-Python: >=3.7,<4.0
Classifier: Development Status :: 5 - Production/Stable
Classifier: Environment :: Console
Classifier: Intended Audience :: Education
Classifier: License :: Freely Distributable
Classifier: License :: OSI Approved :: MIT License
Classifier: Programming Language :: Python :: 3
Classifier: Programming Language :: Python :: 3.10
Classifier: Programming Language :: Python :: 3.7
Classifier: Programming Language :: Python :: 3.8
Classifier: Programming Language :: Python :: 3.9
Classifier: Topic :: Software Development :: Build Tools
Provides-Extra: gui
Requires-Dist: PyQt6 (>=6.2.2,<7.0.0); extra == "gui"
Requires-Dist: gatoryaml (>=1.0.0,<2.0.0)
Requires-Dist: requests (>=2.27.1,<3.0.0)
Requires-Dist: ruamel.yaml (>=0.17.20,<0.18.0)
Requires-Dist: typer (>=0.4.0,<0.5.0)
Project-URL: Repository, https://github.com/cmpsc-481-s22-m1/GatorConfig
